{"exp":1783459216,"data":[{"date_key":"2026-07-01","Compania":"Distribuidora Volkswagen Lomas","Sucursal":"VOLKSWAGEN Lomas","Company":"VW LOMAS","Clientes":"S01-52287","Clientes_Descripcion":"CASA COBO","Folio":"AI0000032701","Fecha":"2026-05-20","Fecha_Venc":"2026-06-19","Condiciones_Pago":"CREDITO 30 DIAS","Rango_Vencido":"000-030 Dias","Vencido_Por_Vencer":"Vencido","Area_de_Negocio":"Autos Nuevos","Tipo_de_Movimiento":"Factura","Clasificacion_de_Cartera":"Aplicado","Cuenta_Contable_CXC":"CUENTAS POR COBRAR AUTOS NUEVOS","Fec_iniOP":"2026-07-01","Fec_finOP":"2026-07-02","Nombre_Mes":"07","Nombre_Mes_Descripcion":"Jul","Fecha_Recepcion_Servicio":"1900-01-01","Marcaje":"SIN FECHA","VIN":"9BWKL45U2TP073911","Tipo_de_Vehiculo":"SAVEIRO","Ano_Modelo":"2026","Monto_Pagado":"SIN PAGOS","Dias_Vencido":13,"Cargos_Creditos":0,"Saldo":330890,"Saldo_Vencido":330890,"Saldo_por_Vencer":0,"Monto_Original":330890,"Dias_en_Taller":0,"Dias_Antiguedad":43},{"date_key":"2026-07-01","Compania":"Distribuidora Volkswagen Lomas","Sucursal":"VOLKSWAGEN Lomas","Company":"VW LOMAS","Clientes":"S01-55433","Clientes_Descripcion":"MOLINERA LA ESPIGA","Folio":"NDI0000014977","Fecha":"2026-06-26","Fecha_Venc":"2026-07-26","Condiciones_Pago":"CREDITO 30 DIAS","Rango_Vencido":"Por Vencer","Vencido_Por_Vencer":"Por Vencer","Area_de_Negocio":"Otros","Tipo_de_Movimiento":"Factura","Clasificacion_de_Cartera":"Aplicado","Cuenta_Contable_CXC":"NOTAS DE CARGO","Fec_iniOP":"2026-07-01","Fec_finOP":"2026-07-02","Nombre_Mes":"07","Nombre_Mes_Descripcion":"Jul","Fecha_Recepcion_Servicio":"1900-01-01","Marcaje":"SIN FECHA","VIN":"NA","Tipo_de_Vehiculo":"NA","Ano_Modelo":"NA","Monto_Pagado":"SIN PAGOS","Dias_Vencido":-24,"Cargos_Creditos":0,"Saldo":1200,"Saldo_Vencido":0,"Saldo_por_Vencer":1200,"Monto_Original":1200,"Dias_en_Taller":0,"Dias_Antiguedad":6},{"date_key":"2026-07-01","Compania":"Distribuidora Volkswagen Lomas","Sucursal":"VOLKSWAGEN Lomas","Company":"VW LOMAS","Clientes":"S01-56768","Clientes_Descripcion":"CENTRAL HARINERA","Folio":"AI0000032828","Fecha":"2026-06-13","Fecha_Venc":"2026-07-13","Condiciones_Pago":"CREDITO 30 DIAS","Rango_Vencido":"Por Vencer","Vencido_Por_Vencer":"Por Vencer","Area_de_Negocio":"Autos Nuevos","Tipo_de_Movimiento":"Factura","Clasificacion_de_Cartera":"Aplicado","Cuenta_Contable_CXC":"CUENTAS POR COBRAR AUTOS NUEVOS","Fec_iniOP":"2026-07-01","Fec_finOP":"2026-07-02","Nombre_Mes":"07","Nombre_Mes_Descripcion":"Jul","Fecha_Recepcion_Servicio":"1900-01-01","Marcaje":"SIN FECHA","VIN":"9BWAL5BZ0TT664635","Tipo_de_Vehiculo":"POLO","Ano_Modelo":"2026","Monto_Pagado":"SIN PAGOS","Dias_Vencido":-11,"Cargos_Creditos":0,"Saldo":302591,"Saldo_Vencido":0,"Saldo_por_Vencer":302591,"Monto_Original":302591,"Dias_en_Taller":0,"Dias_Antiguedad":19},{"date_key":"2026-07-01","Compania":"Distribuidora Volkswagen Lomas","Sucursal":"VOLKSWAGEN Lomas","Company":"VW LOMAS","Clientes":"S01-972","Clientes_Descripcion":"MULTIASISTENCIA","Folio":"RI0000121629","Fecha":"2026-04-29","Fecha_Venc":"2026-05-29","Condiciones_Pago":"NA","Rango_Vencido":"031-060 Dias","Vencido_Por_Vencer":"Vencido","Area_de_Negocio":"Refacciones","Tipo_de_Movimiento":"Factura","Clasificacion_de_Cartera":"Aplicado","Cuenta_Contable_CXC":"CUENTAS POR COBRAR REFACCIONES","Fec_iniOP":"2026-07-01","Fec_finOP":"2026-07-02","Nombre_Mes":"07","Nombre_Mes_Descripcion":"Jul","Fecha_Recepcion_Servicio":"1900-01-01","Marcaje":"SIN FECHA","VIN":"NA","Tipo_de_Vehiculo":"NA","Ano_Modelo":"NA","Monto_Pagado":"SIN PAGOS","Dias_Vencido":34,"Cargos_Creditos":0,"Saldo":7134,"Saldo_Vencido":7134,"Saldo_por_Vencer":0,"Monto_Original":7134,"Dias_en_Taller":0,"Dias_Antiguedad":64},{"date_key":"2026-07-01","Compania":"Distribuidora Volkswagen Lomas","Sucursal":"VOLKSWAGEN Lomas","Company":"VW LOMAS","Clientes":"S01-53454","Clientes_Descripcion":"MANROLAND LATINA","Folio":"SI0000060705","Fecha":"2026-06-29","Fecha_Venc":"2026-07-14","Condiciones_Pago":"NA","Rango_Vencido":"Por Vencer","Vencido_Por_Vencer":"Por Vencer","Area_de_Negocio":"Servicio","Tipo_de_Movimiento":"Factura","Clasificacion_de_Cartera":"Aplicado","Cuenta_Contable_CXC":"CUENTAS POR COBRAR SERVICIO","Fec_iniOP":"2026-07-01","Fec_finOP":"2026-07-02","Nombre_Mes":"07","Nombre_Mes_Descripcion":"Jul","Fecha_Recepcion_Servicio":"1900-01-01","Marcaje":"SIN FECHA","VIN":"3VVJA65N0RM122829","Tipo_de_Vehiculo":"TIGUAN","Ano_Modelo":"2024","Monto_Pagado":"SIN PAGOS","Dias_Vencido":-12,"Cargos_Creditos":0,"Saldo":8490.1396484375,"Saldo_Vencido":0,"Saldo_por_Vencer":8490.1396484375,"Monto_Original":8490.1396484375,"Dias_en_Taller":0,"Dias_Antiguedad":3},{"date_key":"2026-07-01","Compania":"Distribuidora Volkswagen Lomas","Sucursal":"VOLKSWAGEN Lomas","Company":"VW LOMAS","Clientes":"S01-53454","Clientes_Descripcion":"MANROLAND LATINA","Folio":"SI0000060546","Fecha":"2026-06-10","Fecha_Venc":"2026-06-25","Condiciones_Pago":"NA","Rango_Vencido":"000-030 Dias","Vencido_Por_Vencer":"Vencido","Area_de_Negocio":"Servicio","Tipo_de_Movimiento":"Factura","Clasificacion_de_Cartera":"Aplicado","Cuenta_Contable_CXC":"CUENTAS POR COBRAR SERVICIO","Fec_iniOP":"2026-07-01","Fec_finOP":"2026-07-02","Nombre_Mes":"07","Nombre_Mes_Descripcion":"Jul","Fecha_Recepcion_Servicio":"1900-01-01","Marcaje":"SIN FECHA","VIN":"3VVJA65N0RM122829","Tipo_de_Vehiculo":"TIGUAN","Ano_Modelo":"2024","Monto_Pagado":"SIN PAGOS","Dias_Vencido":7,"Cargos_Creditos":0,"Saldo":5508.85009765625,"Saldo_Vencido":5508.85009765625,"Saldo_por_Vencer":0,"Monto_Original":5508.85009765625,"Dias_en_Taller":0,"Dias_Antiguedad":22},{"date_key":"2026-07-01","Compania":"Distribuidora Volkswagen Lomas","Sucursal":"VOLKSWAGEN Lomas","Company":"VW LOMAS","Clientes":"S01-3738","Clientes_Descripcion":"AXA SEGUROS","Folio":"RI0000122537","Fecha":"2026-06-30","Fecha_Venc":"2026-07-30","Condiciones_Pago":"NA","Rango_Vencido":"Por Vencer","Vencido_Por_Vencer":"Por Vencer","Area_de_Negocio":"Refacciones","Tipo_de_Movimiento":"Factura","Clasificacion_de_Cartera":"Aplicado","Cuenta_Contable_CXC":"CUENTAS POR COBRAR REFACCIONES","Fec_iniOP":"2026-07-01","Fec_finOP":"2026-07-02","Nombre_Mes":"07","Nombre_Mes_Descripcion":"Jul","Fecha_Recepcion_Servicio":"1900-01-01","Marcaje":"SIN FECHA","VIN":"NA","Tipo_de_Vehiculo":"NA","Ano_Modelo":"NA","Monto_Pagado":"SIN PAGOS","Dias_Vencido":-28,"Cargos_Creditos":0,"Saldo":13047.6796875,"Saldo_Vencido":0,"Saldo_por_Vencer":13047.6796875,"Monto_Original":13047.6796875,"Dias_en_Taller":0,"Dias_Antiguedad":2},{"date_key":"2026-07-01","Compania":"Distribuidora Volkswagen Lomas","Sucursal":"VOLKSWAGEN Lomas","Company":"VW LOMAS","Clientes":"S01-9009","Clientes_Descripcion":"GENERAL DE SEGUROS","Folio":"SI0000060445","Fecha":"2026-05-29","Fecha_Venc":"2026-06-28","Condiciones_Pago":"NA","Rango_Vencido":"000-030 Dias","Vencido_Por_Vencer":"Vencido","Area_de_Negocio":"Servicio","Tipo_de_Movimiento":"Factura","Clasificacion_de_Cartera":"Aplicado","Cuenta_Contable_CXC":"CUENTAS POR COBRAR SERVICIO","Fec_iniOP":"2026-07-01","Fec_finOP":"2026-07-02","Nombre_Mes":"07","Nombre_Mes_Descripcion":"Jul","Fecha_Recepcion_Servicio":"1900-01-01","Marcaje":"SIN FECHA","VIN":"WVW3N4D28ST013632","Tipo_de_Vehiculo":"VIRTUS","Ano_Modelo":"2025","Monto_Pagado":"SIN PAGOS","Dias_Vencido":4,"Cargos_Creditos":0,"Saldo":5531.10986328125,"Saldo_Vencido":5531.10986328125,"Saldo_por_Vencer":0,"Monto_Original":5531.10986328125,"Dias_en_Taller":0,"Dias_Antiguedad":34},{"date_key":"2026-07-01","Compania":"Distribuidora Volkswagen Lomas","Sucursal":"VOLKSWAGEN Lomas","Company":"VW LOMAS","Clientes":"S01-9009","Clientes_Descripcion":"GENERAL DE SEGUROS","Folio":"SI0000060444","Fecha":"2026-05-29","Fecha_Venc":"2026-06-28","Condiciones_Pago":"NA","Rango_Vencido":"000-030 Dias","Vencido_Por_Vencer":"Vencido","Area_de_Negocio":"Servicio","Tipo_de_Movimiento":"Factura","Clasificacion_de_Cartera":"Aplicado","Cuenta_Contable_CXC":"CUENTAS POR COBRAR SERVICIO","Fec_iniOP":"2026-07-01","Fec_finOP":"2026-07-02","Nombre_Mes":"07","Nombre_Mes_Descripcion":"Jul","Fecha_Recepcion_Servicio":"1900-01-01","Marcaje":"SIN FECHA","VIN":"WVW3N4D28ST013632","Tipo_de_Vehiculo":"VIRTUS","Ano_Modelo":"2025","Monto_Pagado":"SIN PAGOS","Dias_Vencido":4,"Cargos_Creditos":0,"Saldo":31171.30078125,"Saldo_Vencido":31171.30078125,"Saldo_por_Vencer":0,"Monto_Original":31171.30078125,"Dias_en_Taller":0,"Dias_Antiguedad":34},{"date_key":"2026-07-01","Compania":"Distribuidora Volkswagen Lomas","Sucursal":"VOLKSWAGEN Lomas","Company":"VW LOMAS","Clientes":"S01-63","Clientes_Descripcion":"ALLIANZ MEXICO SA COMPA\u00d1IA DE SEGUROS","Folio":"RI0000122363","Fecha":"2026-06-22","Fecha_Venc":"2026-07-07","Condiciones_Pago":"NA","Rango_Vencido":"Por Vencer","Vencido_Por_Vencer":"Por Vencer","Area_de_Negocio":"Refacciones","Tipo_de_Movimiento":"Factura","Clasificacion_de_Cartera":"Aplicado","Cuenta_Contable_CXC":"CUENTAS POR COBRAR REFACCIONES","Fec_iniOP":"2026-07-01","Fec_finOP":"2026-07-02","Nombre_Mes":"07","Nombre_Mes_Descripcion":"Jul","Fecha_Recepcion_Servicio":"1900-01-01","Marcaje":"SIN FECHA","VIN":"NA","Tipo_de_Vehiculo":"NA","Ano_Modelo":"NA","Monto_Pagado":"SIN PAGOS","Dias_Vencido":-5,"Cargos_Creditos":0,"Saldo":1231.9200439453125,"Saldo_Vencido":0,"Saldo_por_Vencer":1231.9200439453125,"Monto_Original":1231.9200439453125,"Dias_en_Taller":0,"Dias_Antiguedad":10},{"date_key":"2026-07-01","Compania":"Distribuidora Volkswagen Lomas","Sucursal":"VOLKSWAGEN Lomas","Company":"VW LOMAS","Clientes":"S01-63","Clientes_Descripcion":"ALLIANZ MEXICO SA COMPA\u00d1IA DE SEGUROS","Folio":"SI0000060628","Fecha":"2026-06-20","Fecha_Venc":"2026-07-05","Condiciones_Pago":"NA","Rango_Vencido":"Por Vencer","Vencido_Por_Vencer":"Por Vencer","Area_de_Negocio":"Servicio","Tipo_de_Movimiento":"Factura","Clasificacion_de_Cartera":"Aplicado","Cuenta_Contable_CXC":"CUENTAS POR COBRAR SERVICIO","Fec_iniOP":"2026-07-01","Fec_finOP":"2026-07-02","Nombre_Mes":"07","Nombre_Mes_Descripcion":"Jul","Fecha_Recepcion_Servicio":"1900-01-01","Marcaje":"SIN FECHA","VIN":"3VVHP65N4PM049152","Tipo_de_Vehiculo":"TIGUAN","Ano_Modelo":"2023","Monto_Pagado":"SIN PAGOS","Dias_Vencido":-3,"Cargos_Creditos":0,"Saldo":4060,"Saldo_Vencido":0,"Saldo_por_Vencer":4060,"Monto_Original":4060,"Dias_en_Taller":0,"Dias_Antiguedad":12},{"date_key":"2026-07-01","Compania":"Distribuidora Volkswagen Lomas","Sucursal":"VOLKSWAGEN Lomas","Company":"VW LOMAS","Clientes":"S01-63","Clientes_Descripcion":"ALLIANZ MEXICO SA COMPA\u00d1IA DE SEGUROS","Folio":"SI0000060627","Fecha":"2026-06-20","Fecha_Venc":"2026-07-05","Condiciones_Pago":"NA","Rango_Vencido":"Por Vencer","Vencido_Por_Vencer":"Por Vencer","Area_de_Negocio":"Servicio","Tipo_de_Movimiento":"Factura","Clasificacion_de_Cartera":"Aplicado","Cuenta_Contable_CXC":"CUENTAS POR COBRAR SERVICIO","Fec_iniOP":"2026-07-01","Fec_finOP":"2026-07-02","Nombre_Mes":"07","Nombre_Mes_Descripcion":"Jul","Fecha_Recepcion_Servicio":"1900-01-01","Marcaje":"SIN FECHA","VIN":"3VVHP65N4PM049152","Tipo_de_Vehiculo":"TIGUAN","Ano_Modelo":"2023","Monto_Pagado":"SIN PAGOS","Dias_Vencido":-3,"Cargos_Creditos":0,"Saldo":15067.98046875,"Saldo_Vencido":0,"Saldo_por_Vencer":15067.98046875,"Monto_Original":15067.98046875,"Dias_en_Taller":0,"Dias_Antiguedad":12},{"date_key":"2026-07-01","Compania":"Distribuidora Volkswagen Lomas","Sucursal":"VOLKSWAGEN Lomas","Company":"VW LOMAS","Clientes":"S01-55434","Clientes_Descripcion":"MOLINERA DE MEXICO","Folio":"AI0000032845","Fecha":"2026-06-16","Fecha_Venc":"2026-07-16","Condiciones_Pago":"CREDITO 30 DIAS","Rango_Vencido":"Por Vencer","Vencido_Por_Vencer":"Por Vencer","Area_de_Negocio":"Autos Nuevos","Tipo_de_Movimiento":"Factura","Clasificacion_de_Cartera":"Aplicado","Cuenta_Contable_CXC":"CUENTAS POR COBRAR AUTOS NUEVOS","Fec_iniOP":"2026-07-01","Fec_finOP":"2026-07-02","Nombre_Mes":"07","Nombre_Mes_Descripcion":"Jul","Fecha_Recepcion_Servicio":"1900-01-01","Marcaje":"SIN FECHA","VIN":"9BWAL5BZ9TT664634","Tipo_de_Vehiculo":"POLO","Ano_Modelo":"2026","Monto_Pagado":"SIN PAGOS","Dias_Vencido":-14,"Cargos_Creditos":0,"Saldo":302591,"Saldo_Vencido":0,"Saldo_por_Vencer":302591,"Monto_Original":302591,"Dias_en_Taller":0,"Dias_Antiguedad":16},{"date_key":"2026-07-01","Compania":"Distribuidora Volkswagen Lomas","Sucursal":"VOLKSWAGEN Lomas","Company":"VW LOMAS","Clientes":"S01-55135","Clientes_Descripcion":"Y 365 ADMINISTRADORA","Folio":"RI0000122511","Fecha":"2026-06-27","Fecha_Venc":"2026-07-12","Condiciones_Pago":"NA","Rango_Vencido":"Por Vencer","Vencido_Por_Vencer":"Por Vencer","Area_de_Negocio":"Refacciones","Tipo_de_Movimiento":"Factura","Clasificacion_de_Cartera":"Aplicado","Cuenta_Contable_CXC":"CUENTAS POR COBRAR REFACCIONES","Fec_iniOP":"2026-07-01","Fec_finOP":"2026-07-02","Nombre_Mes":"07","Nombre_Mes_Descripcion":"Jul","Fecha_Recepcion_Servicio":"1900-01-01","Marcaje":"SIN FECHA","VIN":"NA","Tipo_de_Vehiculo":"NA","Ano_Modelo":"NA","Monto_Pagado":"SIN PAGOS","Dias_Vencido":-10,"Cargos_Creditos":0,"Saldo":21520.439453125,"Saldo_Vencido":0,"Saldo_por_Vencer":21520.439453125,"Monto_Original":21520.439453125,"Dias_en_Taller":0,"Dias_Antiguedad":5},{"date_key":"2026-07-01","Compania":"Distribuidora Volkswagen Lomas","Sucursal":"VOLKSWAGEN Lomas","Company":"VW LOMAS","Clientes":"S01-55135","Clientes_Descripcion":"Y 365 ADMINISTRADORA","Folio":"RI0000122510","Fecha":"2026-06-27","Fecha_Venc":"2026-07-12","Condiciones_Pago":"NA","Rango_Vencido":"Por Vencer","Vencido_Por_Vencer":"Por Vencer","Area_de_Negocio":"Refacciones","Tipo_de_Movimiento":"Factura","Clasificacion_de_Cartera":"Aplicado","Cuenta_Contable_CXC":"CUENTAS POR COBRAR REFACCIONES","Fec_iniOP":"2026-07-01","Fec_finOP":"2026-07-02","Nombre_Mes":"07","Nombre_Mes_Descripcion":"Jul","Fecha_Recepcion_Servicio":"1900-01-01","Marcaje":"SIN FECHA","VIN":"NA","Tipo_de_Vehiculo":"NA","Ano_Modelo":"NA","Monto_Pagado":"SIN PAGOS","Dias_Vencido":-10,"Cargos_Creditos":0,"Saldo":30589.19921875,"Saldo_Vencido":0,"Saldo_por_Vencer":30589.19921875,"Monto_Original":30589.19921875,"Dias_en_Taller":0,"Dias_Antiguedad":5},{"date_key":"2026-07-01","Compania":"Distribuidora Volkswagen Lomas","Sucursal":"VOLKSWAGEN Lomas","Company":"VW LOMAS","Clientes":"S01-48228","Clientes_Descripcion":"ZURICH ASEGURADORA MEXICANA","Folio":"RI0000122539","Fecha":"2026-06-30","Fecha_Venc":"2026-07-07","Condiciones_Pago":"NA","Rango_Vencido":"Por Vencer","Vencido_Por_Vencer":"Por Vencer","Area_de_Negocio":"Refacciones","Tipo_de_Movimiento":"Factura","Clasificacion_de_Cartera":"Aplicado","Cuenta_Contable_CXC":"CUENTAS POR COBRAR REFACCIONES","Fec_iniOP":"2026-07-01","Fec_finOP":"2026-07-02","Nombre_Mes":"07","Nombre_Mes_Descripcion":"Jul","Fecha_Recepcion_Servicio":"1900-01-01","Marcaje":"SIN FECHA","VIN":"NA","Tipo_de_Vehiculo":"NA","Ano_Modelo":"NA","Monto_Pagado":"SIN PAGOS","Dias_Vencido":-5,"Cargos_Creditos":0,"Saldo":841,"Saldo_Vencido":0,"Saldo_por_Vencer":841,"Monto_Original":841,"Dias_en_Taller":0,"Dias_Antiguedad":2},{"date_key":"2026-07-01","Compania":"Distribuidora Volkswagen Lomas","Sucursal":"VOLKSWAGEN Lomas","Company":"VW LOMAS","Clientes":"S01-48228","Clientes_Descripcion":"ZURICH ASEGURADORA MEXICANA","Folio":"RI0000122538","Fecha":"2026-06-30","Fecha_Venc":"2026-07-07","Condiciones_Pago":"NA","Rango_Vencido":"Por Vencer","Vencido_Por_Vencer":"Por Vencer","Area_de_Negocio":"Refacciones","Tipo_de_Movimiento":"Factura","Clasificacion_de_Cartera":"Aplicado","Cuenta_Contable_CXC":"CUENTAS POR COBRAR REFACCIONES","Fec_iniOP":"2026-07-01","Fec_finOP":"2026-07-02","Nombre_Mes":"07","Nombre_Mes_Descripcion":"Jul","Fecha_Recepcion_Servicio":"1900-01-01","Marcaje":"SIN FECHA","VIN":"NA","Tipo_de_Vehiculo":"NA","Ano_Modelo":"NA","Monto_Pagado":"SIN PAGOS","Dias_Vencido":-5,"Cargos_Creditos":0,"Saldo":78026.2421875,"Saldo_Vencido":0,"Saldo_por_Vencer":78026.2421875,"Monto_Original":78026.2421875,"Dias_en_Taller":0,"Dias_Antiguedad":2},{"date_key":"2026-07-01","Compania":"Distribuidora Volkswagen Lomas","Sucursal":"VOLKSWAGEN Lomas","Company":"VW LOMAS","Clientes":"S01-48228","Clientes_Descripcion":"ZURICH ASEGURADORA MEXICANA","Folio":"RI0000122536","Fecha":"2026-06-30","Fecha_Venc":"2026-07-07","Condiciones_Pago":"NA","Rango_Vencido":"Por Vencer","Vencido_Por_Vencer":"Por Vencer","Area_de_Negocio":"Refacciones","Tipo_de_Movimiento":"Factura","Clasificacion_de_Cartera":"Aplicado","Cuenta_Contable_CXC":"CUENTAS POR COBRAR REFACCIONES","Fec_iniOP":"2026-07-01","Fec_finOP":"2026-07-02","Nombre_Mes":"07","Nombre_Mes_Descripcion":"Jul","Fecha_Recepcion_Servicio":"1900-01-01","Marcaje":"SIN FECHA","VIN":"NA","Tipo_de_Vehiculo":"NA","Ano_Modelo":"NA","Monto_Pagado":"SIN PAGOS","Dias_Vencido":-5,"Cargos_Creditos":0,"Saldo":47718.921875,"Saldo_Vencido":0,"Saldo_por_Vencer":47718.921875,"Monto_Original":47718.921875,"Dias_en_Taller":0,"Dias_Antiguedad":2},{"date_key":"2026-07-01","Compania":"Distribuidora Volkswagen Lomas","Sucursal":"VOLKSWAGEN Lomas","Company":"VW LOMAS","Clientes":"S01-48228","Clientes_Descripcion":"ZURICH ASEGURADORA MEXICANA","Folio":"RI0000122503","Fecha":"2026-06-26","Fecha_Venc":"2026-07-03","Condiciones_Pago":"NA","Rango_Vencido":"Por Vencer","Vencido_Por_Vencer":"Por Vencer","Area_de_Negocio":"Refacciones","Tipo_de_Movimiento":"Factura","Clasificacion_de_Cartera":"Aplicado","Cuenta_Contable_CXC":"CUENTAS POR COBRAR REFACCIONES","Fec_iniOP":"2026-07-01","Fec_finOP":"2026-07-02","Nombre_Mes":"07","Nombre_Mes_Descripcion":"Jul","Fecha_Recepcion_Servicio":"1900-01-01","Marcaje":"SIN FECHA","VIN":"NA","Tipo_de_Vehiculo":"NA","Ano_Modelo":"NA","Monto_Pagado":"SIN PAGOS","Dias_Vencido":-1,"Cargos_Creditos":0,"Saldo":1740,"Saldo_Vencido":0,"Saldo_por_Vencer":1740,"Monto_Original":1740,"Dias_en_Taller":0,"Dias_Antiguedad":6},{"date_key":"2026-07-01","Compania":"Distribuidora Volkswagen Lomas","Sucursal":"VOLKSWAGEN Lomas","Company":"VW LOMAS","Clientes":"S01-48228","Clientes_Descripcion":"ZURICH ASEGURADORA MEXICANA","Folio":"RI0000122502","Fecha":"2026-06-26","Fecha_Venc":"2026-07-03","Condiciones_Pago":"NA","Rango_Vencido":"Por Vencer","Vencido_Por_Vencer":"Por Vencer","Area_de_Negocio":"Refacciones","Tipo_de_Movimiento":"Factura","Clasificacion_de_Cartera":"Aplicado","Cuenta_Contable_CXC":"CUENTAS POR COBRAR REFACCIONES","Fec_iniOP":"2026-07-01","Fec_finOP":"2026-07-02","Nombre_Mes":"07","Nombre_Mes_Descripcion":"Jul","Fecha_Recepcion_Servicio":"1900-01-01","Marcaje":"SIN FECHA","VIN":"NA","Tipo_de_Vehiculo":"NA","Ano_Modelo":"NA","Monto_Pagado":"SIN PAGOS","Dias_Vencido":-1,"Cargos_Creditos":0,"Saldo":23564.240234375,"Saldo_Vencido":0,"Saldo_por_Vencer":23564.240234375,"Monto_Original":23564.240234375,"Dias_en_Taller":0,"Dias_Antiguedad":6},{"date_key":"2026-07-01","Compania":"Distribuidora Volkswagen Lomas","Sucursal":"VOLKSWAGEN Lomas","Company":"VW LOMAS","Clientes":"S01-48228","Clientes_Descripcion":"ZURICH ASEGURADORA MEXICANA","Folio":"RI0000122501","Fecha":"2026-06-26","Fecha_Venc":"2026-07-03","Condiciones_Pago":"NA","Rango_Vencido":"Por Vencer","Vencido_Por_Vencer":"Por Vencer","Area_de_Negocio":"Refacciones","Tipo_de_Movimiento":"Factura","Clasificacion_de_Cartera":"Aplicado","Cuenta_Contable_CXC":"CUENTAS POR COBRAR REFACCIONES","Fec_iniOP":"2026-07-01","Fec_finOP":"2026-07-02","Nombre_Mes":"07","Nombre_Mes_Descripcion":"Jul","Fecha_Recepcion_Servicio":"1900-01-01","Marcaje":"SIN FECHA","VIN":"NA","Tipo_de_Vehiculo":"NA","Ano_Modelo":"NA","Monto_Pagado":"SIN PAGOS","Dias_Vencido":-1,"Cargos_Creditos":0,"Saldo":1009.2000122070312,"Saldo_Vencido":0,"Saldo_por_Vencer":1009.2000122070312,"Monto_Original":1009.2000122070312,"Dias_en_Taller":0,"Dias_Antiguedad":6},{"date_key":"2026-07-01","Compania":"Distribuidora Volkswagen Lomas","Sucursal":"VOLKSWAGEN Lomas","Company":"VW LOMAS","Clientes":"S01-48228","Clientes_Descripcion":"ZURICH ASEGURADORA MEXICANA","Folio":"RI0000122499","Fecha":"2026-06-26","Fecha_Venc":"2026-07-03","Condiciones_Pago":"NA","Rango_Vencido":"Por Vencer","Vencido_Por_Vencer":"Por Vencer","Area_de_Negocio":"Refacciones","Tipo_de_Movimiento":"Factura","Clasificacion_de_Cartera":"Aplicado","Cuenta_Contable_CXC":"CUENTAS POR COBRAR REFACCIONES","Fec_iniOP":"2026-07-01","Fec_finOP":"2026-07-02","Nombre_Mes":"07","Nombre_Mes_Descripcion":"Jul","Fecha_Recepcion_Servicio":"1900-01-01","Marcaje":"SIN FECHA","VIN":"NA","Tipo_de_Vehiculo":"NA","Ano_Modelo":"NA","Monto_Pagado":"SIN PAGOS","Dias_Vencido":-1,"Cargos_Creditos":0,"Saldo":11351.759765625,"Saldo_Vencido":0,"Saldo_por_Vencer":11351.759765625,"Monto_Original":11351.759765625,"Dias_en_Taller":0,"Dias_Antiguedad":6},{"date_key":"2026-07-01","Compania":"Distribuidora Volkswagen Lomas","Sucursal":"VOLKSWAGEN Lomas","Company":"VW LOMAS","Clientes":"S01-48228","Clientes_Descripcion":"ZURICH ASEGURADORA MEXICANA","Folio":"RI0000122498","Fecha":"2026-06-26","Fecha_Venc":"2026-07-03","Condiciones_Pago":"NA","Rango_Vencido":"Por Vencer","Vencido_Por_Vencer":"Por Vencer","Area_de_Negocio":"Refacciones","Tipo_de_Movimiento":"Factura","Clasificacion_de_Cartera":"Aplicado","Cuenta_Contable_CXC":"CUENTAS POR COBRAR REFACCIONES","Fec_iniOP":"2026-07-01","Fec_finOP":"2026-07-02","Nombre_Mes":"07","Nombre_Mes_Descripcion":"Jul","Fecha_Recepcion_Servicio":"1900-01-01","Marcaje":"SIN FECHA","VIN":"NA","Tipo_de_Vehiculo":"NA","Ano_Modelo":"NA","Monto_Pagado":"SIN PAGOS","Dias_Vencido":-1,"Cargos_Creditos":0,"Saldo":37358.9609375,"Saldo_Vencido":0,"Saldo_por_Vencer":37358.9609375,"Monto_Original":37358.9609375,"Dias_en_Taller":0,"Dias_Antiguedad":6},{"date_key":"2026-07-01","Compania":"Distribuidora Volkswagen Lomas","Sucursal":"VOLKSWAGEN Lomas","Company":"VW LOMAS","Clientes":"S01-48228","Clientes_Descripcion":"ZURICH ASEGURADORA MEXICANA","Folio":"RI0000122381","Fecha":"2026-06-22","Fecha_Venc":"2026-06-29","Condiciones_Pago":"NA","Rango_Vencido":"000-030 Dias","Vencido_Por_Vencer":"Vencido","Area_de_Negocio":"Refacciones","Tipo_de_Movimiento":"Factura","Clasificacion_de_Cartera":"Aplicado","Cuenta_Contable_CXC":"CUENTAS POR COBRAR REFACCIONES","Fec_iniOP":"2026-07-01","Fec_finOP":"2026-07-02","Nombre_Mes":"07","Nombre_Mes_Descripcion":"Jul","Fecha_Recepcion_Servicio":"1900-01-01","Marcaje":"SIN FECHA","VIN":"NA","Tipo_de_Vehiculo":"NA","Ano_Modelo":"NA","Monto_Pagado":"SIN PAGOS","Dias_Vencido":3,"Cargos_Creditos":0,"Saldo":812,"Saldo_Vencido":812,"Saldo_por_Vencer":0,"Monto_Original":812,"Dias_en_Taller":0,"Dias_Antiguedad":10},{"date_key":"2026-07-01","Compania":"Distribuidora Volkswagen Lomas","Sucursal":"VOLKSWAGEN Lomas","Company":"VW LOMAS","Clientes":"S01-48228","Clientes_Descripcion":"ZURICH ASEGURADORA MEXICANA","Folio":"RI0000122380","Fecha":"2026-06-22","Fecha_Venc":"2026-06-29","Condiciones_Pago":"NA","Rango_Vencido":"000-030 Dias","Vencido_Por_Vencer":"Vencido","Area_de_Negocio":"Refacciones","Tipo_de_Movimiento":"Factura","Clasificacion_de_Cartera":"Aplicado","Cuenta_Contable_CXC":"CUENTAS POR COBRAR REFACCIONES","Fec_iniOP":"2026-07-01","Fec_finOP":"2026-07-02","Nombre_Mes":"07","Nombre_Mes_Descripcion":"Jul","Fecha_Recepcion_Servicio":"1900-01-01","Marcaje":"SIN FECHA","VIN":"NA","Tipo_de_Vehiculo":"NA","Ano_Modelo":"NA","Monto_Pagado":"SIN PAGOS","Dias_Vencido":3,"Cargos_Creditos":0,"Saldo":6898.52001953125,"Saldo_Vencido":6898.52001953125,"Saldo_por_Vencer":0,"Monto_Original":6898.52001953125,"Dias_en_Taller":0,"Dias_Antiguedad":10},{"date_key":"2026-07-01","Compania":"Distribuidora Volkswagen Lomas","Sucursal":"VOLKSWAGEN Lomas","Company":"VW LOMAS","Clientes":"S01-48228","Clientes_Descripcion":"ZURICH ASEGURADORA MEXICANA","Folio":"RI0000122379","Fecha":"2026-06-22","Fecha_Venc":"2026-06-29","Condiciones_Pago":"NA","Rango_Vencido":"000-030 Dias","Vencido_Por_Vencer":"Vencido","Area_de_Negocio":"Refacciones","Tipo_de_Movimiento":"Factura","Clasificacion_de_Cartera":"Aplicado","Cuenta_Contable_CXC":"CUENTAS POR COBRAR REFACCIONES","Fec_iniOP":"2026-07-01","Fec_finOP":"2026-07-02","Nombre_Mes":"07","Nombre_Mes_Descripcion":"Jul","Fecha_Recepcion_Servicio":"1900-01-01","Marcaje":"SIN FECHA","VIN":"NA","Tipo_de_Vehiculo":"NA","Ano_Modelo":"NA","Monto_Pagado":"SIN PAGOS","Dias_Vencido":3,"Cargos_Creditos":0,"Saldo":2146,"Saldo_Vencido":2146,"Saldo_por_Vencer":0,"Monto_Original":2146,"Dias_en_Taller":0,"Dias_Antiguedad":10},{"date_key":"2026-07-01","Compania":"Distribuidora Volkswagen Lomas","Sucursal":"VOLKSWAGEN Lomas","Company":"VW LOMAS","Clientes":"S01-48228","Clientes_Descripcion":"ZURICH ASEGURADORA MEXICANA","Folio":"RI0000122378","Fecha":"2026-06-22","Fecha_Venc":"2026-06-29","Condiciones_Pago":"NA","Rango_Vencido":"000-030 Dias","Vencido_Por_Vencer":"Vencido","Area_de_Negocio":"Refacciones","Tipo_de_Movimiento":"Factura","Clasificacion_de_Cartera":"Aplicado","Cuenta_Contable_CXC":"CUENTAS POR COBRAR REFACCIONES","Fec_iniOP":"2026-07-01","Fec_finOP":"2026-07-02","Nombre_Mes":"07","Nombre_Mes_Descripcion":"Jul","Fecha_Recepcion_Servicio":"1900-01-01","Marcaje":"SIN FECHA","VIN":"NA","Tipo_de_Vehiculo":"NA","Ano_Modelo":"NA","Monto_Pagado":"SIN PAGOS","Dias_Vencido":3,"Cargos_Creditos":0,"Saldo":46365.19921875,"Saldo_Vencido":46365.19921875,"Saldo_por_Vencer":0,"Monto_Original":46365.19921875,"Dias_en_Taller":0,"Dias_Antiguedad":10},{"date_key":"2026-07-01","Compania":"Distribuidora Volkswagen Lomas","Sucursal":"VOLKSWAGEN Lomas","Company":"VW LOMAS","Clientes":"S01-48228","Clientes_Descripcion":"ZURICH ASEGURADORA MEXICANA","Folio":"RI0000122377","Fecha":"2026-06-22","Fecha_Venc":"2026-06-29","Condiciones_Pago":"NA","Rango_Vencido":"000-030 Dias","Vencido_Por_Vencer":"Vencido","Area_de_Negocio":"Refacciones","Tipo_de_Movimiento":"Factura","Clasificacion_de_Cartera":"Aplicado","Cuenta_Contable_CXC":"CUENTAS POR COBRAR REFACCIONES","Fec_iniOP":"2026-07-01","Fec_finOP":"2026-07-02","Nombre_Mes":"07","Nombre_Mes_Descripcion":"Jul","Fecha_Recepcion_Servicio":"1900-01-01","Marcaje":"SIN FECHA","VIN":"NA","Tipo_de_Vehiculo":"NA","Ano_Modelo":"NA","Monto_Pagado":"SIN PAGOS","Dias_Vencido":3,"Cargos_Creditos":0,"Saldo":8581.6796875,"Saldo_Vencido":8581.6796875,"Saldo_por_Vencer":0,"Monto_Original":8581.6796875,"Dias_en_Taller":0,"Dias_Antiguedad":10},{"date_key":"2026-07-01","Compania":"Distribuidora Volkswagen Lomas","Sucursal":"VOLKSWAGEN Lomas","Company":"VW LOMAS","Clientes":"S01-48228","Clientes_Descripcion":"ZURICH ASEGURADORA MEXICANA","Folio":"RI0000122372","Fecha":"2026-06-22","Fecha_Venc":"2026-06-29","Condiciones_Pago":"NA","Rango_Vencido":"000-030 Dias","Vencido_Por_Vencer":"Vencido","Area_de_Negocio":"Refacciones","Tipo_de_Movimiento":"Factura","Clasificacion_de_Cartera":"Aplicado","Cuenta_Contable_CXC":"CUENTAS POR COBRAR REFACCIONES","Fec_iniOP":"2026-07-01","Fec_finOP":"2026-07-02","Nombre_Mes":"07","Nombre_Mes_Descripcion":"Jul","Fecha_Recepcion_Servicio":"1900-01-01","Marcaje":"SIN FECHA","VIN":"NA","Tipo_de_Vehiculo":"NA","Ano_Modelo":"NA","Monto_Pagado":"SIN PAGOS","Dias_Vencido":3,"Cargos_Creditos":0,"Saldo":3179.56005859375,"Saldo_Vencido":3179.56005859375,"Saldo_por_Vencer":0,"Monto_Original":3179.56005859375,"Dias_en_Taller":0,"Dias_Antiguedad":10},{"date_key":"2026-07-01","Compania":"Distribuidora Volkswagen Lomas","Sucursal":"VOLKSWAGEN Lomas","Company":"VW LOMAS","Clientes":"S01-48228","Clientes_Descripcion":"ZURICH ASEGURADORA MEXICANA","Folio":"RI0000122371","Fecha":"2026-06-22","Fecha_Venc":"2026-06-29","Condiciones_Pago":"NA","Rango_Vencido":"000-030 Dias","Vencido_Por_Vencer":"Vencido","Area_de_Negocio":"Refacciones","Tipo_de_Movimiento":"Factura","Clasificacion_de_Cartera":"Aplicado","Cuenta_Contable_CXC":"CUENTAS POR COBRAR REFACCIONES","Fec_iniOP":"2026-07-01","Fec_finOP":"2026-07-02","Nombre_Mes":"07","Nombre_Mes_Descripcion":"Jul","Fecha_Recepcion_Servicio":"1900-01-01","Marcaje":"SIN FECHA","VIN":"NA","Tipo_de_Vehiculo":"NA","Ano_Modelo":"NA","Monto_Pagado":"SIN PAGOS","Dias_Vencido":3,"Cargos_Creditos":0,"Saldo":22396.119140625,"Saldo_Vencido":22396.119140625,"Saldo_por_Vencer":0,"Monto_Original":22396.119140625,"Dias_en_Taller":0,"Dias_Antiguedad":10},{"date_key":"2026-07-01","Compania":"Distribuidora Volkswagen Lomas","Sucursal":"VOLKSWAGEN Lomas","Company":"VW LOMAS","Clientes":"S01-48228","Clientes_Descripcion":"ZURICH ASEGURADORA MEXICANA","Folio":"RI0000122370","Fecha":"2026-06-22","Fecha_Venc":"2026-06-29","Condiciones_Pago":"NA","Rango_Vencido":"000-030 Dias","Vencido_Por_Vencer":"Vencido","Area_de_Negocio":"Refacciones","Tipo_de_Movimiento":"Factura","Clasificacion_de_Cartera":"Aplicado","Cuenta_Contable_CXC":"CUENTAS POR COBRAR REFACCIONES","Fec_iniOP":"2026-07-01","Fec_finOP":"2026-07-02","Nombre_Mes":"07","Nombre_Mes_Descripcion":"Jul","Fecha_Recepcion_Servicio":"1900-01-01","Marcaje":"SIN FECHA","VIN":"NA","Tipo_de_Vehiculo":"NA","Ano_Modelo":"NA","Monto_Pagado":"SIN PAGOS","Dias_Vencido":3,"Cargos_Creditos":0,"Saldo":2417.43994140625,"Saldo_Vencido":2417.43994140625,"Saldo_por_Vencer":0,"Monto_Original":2417.43994140625,"Dias_en_Taller":0,"Dias_Antiguedad":10},{"date_key":"2026-07-01","Compania":"Distribuidora Volkswagen Lomas","Sucursal":"VOLKSWAGEN Lomas","Company":"VW LOMAS","Clientes":"S01-51132","Clientes_Descripcion":"MARTIN CANALES ISLAS","Folio":"RI0000102956","Fecha":"2023-07-14","Fecha_Venc":"2023-07-14","Condiciones_Pago":"NA","Rango_Vencido":"Mas de 360 Dias","Vencido_Por_Vencer":"Vencido","Area_de_Negocio":"Refacciones","Tipo_de_Movimiento":"Anticipo","Clasificacion_de_Cartera":"Sin Aplicar","Cuenta_Contable_CXC":"CUENTAS POR COBRAR REFACCIONES","Fec_iniOP":"2026-07-01","Fec_finOP":"2026-07-02","Nombre_Mes":"07","Nombre_Mes_Descripcion":"Jul","Fecha_Recepcion_Servicio":"1900-01-01","Marcaje":"SIN FECHA","VIN":"NA","Tipo_de_Vehiculo":"NA","Ano_Modelo":"NA","Monto_Pagado":"$8,651.54","Dias_Vencido":1084,"Cargos_Creditos":0,"Saldo":-1.159999966621399,"Saldo_Vencido":-1.159999966621399,"Saldo_por_Vencer":0,"Monto_Original":8650.3798828125,"Dias_en_Taller":0,"Dias_Antiguedad":1084},{"date_key":"2026-07-01","Compania":"Distribuidora Volkswagen Lomas","Sucursal":"VOLKSWAGEN Lomas","Company":"VW LOMAS","Clientes":"S01-48228","Clientes_Descripcion":"ZURICH ASEGURADORA MEXICANA","Folio":"RI0000122368","Fecha":"2026-06-22","Fecha_Venc":"2026-06-29","Condiciones_Pago":"NA","Rango_Vencido":"000-030 Dias","Vencido_Por_Vencer":"Vencido","Area_de_Negocio":"Refacciones","Tipo_de_Movimiento":"Factura","Clasificacion_de_Cartera":"Aplicado","Cuenta_Contable_CXC":"CUENTAS POR COBRAR REFACCIONES","Fec_iniOP":"2026-07-01","Fec_finOP":"2026-07-02","Nombre_Mes":"07","Nombre_Mes_Descripcion":"Jul","Fecha_Recepcion_Servicio":"1900-01-01","Marcaje":"SIN FECHA","VIN":"NA","Tipo_de_Vehiculo":"NA","Ano_Modelo":"NA","Monto_Pagado":"SIN PAGOS","Dias_Vencido":3,"Cargos_Creditos":0,"Saldo":3454.47998046875,"Saldo_Vencido":3454.47998046875,"Saldo_por_Vencer":0,"Monto_Original":3454.47998046875,"Dias_en_Taller":0,"Dias_Antiguedad":10},{"date_key":"2026-07-01","Compania":"Distribuidora Volkswagen Lomas","Sucursal":"VOLKSWAGEN Lomas","Company":"VW LOMAS","Clientes":"S01-48228","Clientes_Descripcion":"ZURICH ASEGURADORA MEXICANA","Folio":"RI0000122365","Fecha":"2026-06-22","Fecha_Venc":"2026-06-29","Condiciones_Pago":"NA","Rango_Vencido":"000-030 Dias","Vencido_Por_Vencer":"Vencido","Area_de_Negocio":"Refacciones","Tipo_de_Movimiento":"Factura","Clasificacion_de_Cartera":"Aplicado","Cuenta_Contable_CXC":"CUENTAS POR COBRAR REFACCIONES","Fec_iniOP":"2026-07-01","Fec_finOP":"2026-07-02","Nombre_Mes":"07","Nombre_Mes_Descripcion":"Jul","Fecha_Recepcion_Servicio":"1900-01-01","Marcaje":"SIN FECHA","VIN":"NA","Tipo_de_Vehiculo":"NA","Ano_Modelo":"NA","Monto_Pagado":"SIN PAGOS","Dias_Vencido":3,"Cargos_Creditos":0,"Saldo":3394.159912109375,"Saldo_Vencido":3394.159912109375,"Saldo_por_Vencer":0,"Monto_Original":3394.159912109375,"Dias_en_Taller":0,"Dias_Antiguedad":10},{"date_key":"2026-07-01","Compania":"Distribuidora Volkswagen Lomas","Sucursal":"VOLKSWAGEN Lomas","Company":"VW LOMAS","Clientes":"S01-48228","Clientes_Descripcion":"ZURICH ASEGURADORA MEXICANA","Folio":"RI0000122362","Fecha":"2026-06-22","Fecha_Venc":"2026-06-29","Condiciones_Pago":"NA","Rango_Vencido":"000-030 Dias","Vencido_Por_Vencer":"Vencido","Area_de_Negocio":"Refacciones","Tipo_de_Movimiento":"Factura","Clasificacion_de_Cartera":"Aplicado","Cuenta_Contable_CXC":"CUENTAS POR COBRAR REFACCIONES","Fec_iniOP":"2026-07-01","Fec_finOP":"2026-07-02","Nombre_Mes":"07","Nombre_Mes_Descripcion":"Jul","Fecha_Recepcion_Servicio":"1900-01-01","Marcaje":"SIN FECHA","VIN":"NA","Tipo_de_Vehiculo":"NA","Ano_Modelo":"NA","Monto_Pagado":"SIN PAGOS","Dias_Vencido":3,"Cargos_Creditos":0,"Saldo":1568.3199462890625,"Saldo_Vencido":1568.3199462890625,"Saldo_por_Vencer":0,"Monto_Original":1568.3199462890625,"Dias_en_Taller":0,"Dias_Antiguedad":10},{"date_key":"2026-07-01","Compania":"Distribuidora Volkswagen Lomas","Sucursal":"VOLKSWAGEN Lomas","Company":"VW LOMAS","Clientes":"S01-42363","Clientes_Descripcion":"CHUBB SEGUROS MEXICO","Folio":"RI0000122520","Fecha":"2026-06-29","Fecha_Venc":"2026-07-14","Condiciones_Pago":"NA","Rango_Vencido":"Por Vencer","Vencido_Por_Vencer":"Por Vencer","Area_de_Negocio":"Refacciones","Tipo_de_Movimiento":"Factura","Clasificacion_de_Cartera":"Aplicado","Cuenta_Contable_CXC":"CUENTAS POR COBRAR REFACCIONES","Fec_iniOP":"2026-07-01","Fec_finOP":"2026-07-02","Nombre_Mes":"07","Nombre_Mes_Descripcion":"Jul","Fecha_Recepcion_Servicio":"1900-01-01","Marcaje":"SIN FECHA","VIN":"NA","Tipo_de_Vehiculo":"NA","Ano_Modelo":"NA","Monto_Pagado":"SIN PAGOS","Dias_Vencido":-12,"Cargos_Creditos":0,"Saldo":997.5999755859375,"Saldo_Vencido":0,"Saldo_por_Vencer":997.5999755859375,"Monto_Original":997.5999755859375,"Dias_en_Taller":0,"Dias_Antiguedad":3},{"date_key":"2026-07-01","Compania":"Distribuidora Volkswagen Lomas","Sucursal":"VOLKSWAGEN Lomas","Company":"VW LOMAS","Clientes":"S01-42363","Clientes_Descripcion":"CHUBB SEGUROS MEXICO","Folio":"RI0000122515","Fecha":"2026-06-29","Fecha_Venc":"2026-07-14","Condiciones_Pago":"NA","Rango_Vencido":"Por Vencer","Vencido_Por_Vencer":"Por Vencer","Area_de_Negocio":"Refacciones","Tipo_de_Movimiento":"Factura","Clasificacion_de_Cartera":"Aplicado","Cuenta_Contable_CXC":"CUENTAS POR COBRAR REFACCIONES","Fec_iniOP":"2026-07-01","Fec_finOP":"2026-07-02","Nombre_Mes":"07","Nombre_Mes_Descripcion":"Jul","Fecha_Recepcion_Servicio":"1900-01-01","Marcaje":"SIN FECHA","VIN":"NA","Tipo_de_Vehiculo":"NA","Ano_Modelo":"NA","Monto_Pagado":"SIN PAGOS","Dias_Vencido":-12,"Cargos_Creditos":0,"Saldo":788.7999877929688,"Saldo_Vencido":0,"Saldo_por_Vencer":788.7999877929688,"Monto_Original":788.7999877929688,"Dias_en_Taller":0,"Dias_Antiguedad":3},{"date_key":"2026-07-01","Compania":"Distribuidora Volkswagen Lomas","Sucursal":"VOLKSWAGEN Lomas","Company":"VW LOMAS","Clientes":"S01-42363","Clientes_Descripcion":"CHUBB SEGUROS MEXICO","Folio":"RI0000122496","Fecha":"2026-06-26","Fecha_Venc":"2026-07-11","Condiciones_Pago":"NA","Rango_Vencido":"Por Vencer","Vencido_Por_Vencer":"Por Vencer","Area_de_Negocio":"Refacciones","Tipo_de_Movimiento":"Factura","Clasificacion_de_Cartera":"Aplicado","Cuenta_Contable_CXC":"CUENTAS POR COBRAR REFACCIONES","Fec_iniOP":"2026-07-01","Fec_finOP":"2026-07-02","Nombre_Mes":"07","Nombre_Mes_Descripcion":"Jul","Fecha_Recepcion_Servicio":"1900-01-01","Marcaje":"SIN FECHA","VIN":"NA","Tipo_de_Vehiculo":"NA","Ano_Modelo":"NA","Monto_Pagado":"SIN PAGOS","Dias_Vencido":-9,"Cargos_Creditos":0,"Saldo":628.719970703125,"Saldo_Vencido":0,"Saldo_por_Vencer":628.719970703125,"Monto_Original":628.719970703125,"Dias_en_Taller":0,"Dias_Antiguedad":6},{"date_key":"2026-07-01","Compania":"Distribuidora Volkswagen Lomas","Sucursal":"VOLKSWAGEN Lomas","Company":"VW LOMAS","Clientes":"S01-42363","Clientes_Descripcion":"CHUBB SEGUROS MEXICO","Folio":"RI0000122493","Fecha":"2026-06-26","Fecha_Venc":"2026-07-11","Condiciones_Pago":"NA","Rango_Vencido":"Por Vencer","Vencido_Por_Vencer":"Por Vencer","Area_de_Negocio":"Refacciones","Tipo_de_Movimiento":"Factura","Clasificacion_de_Cartera":"Aplicado","Cuenta_Contable_CXC":"CUENTAS POR COBRAR REFACCIONES","Fec_iniOP":"2026-07-01","Fec_finOP":"2026-07-02","Nombre_Mes":"07","Nombre_Mes_Descripcion":"Jul","Fecha_Recepcion_Servicio":"1900-01-01","Marcaje":"SIN FECHA","VIN":"NA","Tipo_de_Vehiculo":"NA","Ano_Modelo":"NA","Monto_Pagado":"SIN PAGOS","Dias_Vencido":-9,"Cargos_Creditos":0,"Saldo":1392,"Saldo_Vencido":0,"Saldo_por_Vencer":1392,"Monto_Original":1392,"Dias_en_Taller":0,"Dias_Antiguedad":6},{"date_key":"2026-07-01","Compania":"Distribuidora Volkswagen Lomas","Sucursal":"VOLKSWAGEN Lomas","Company":"VW LOMAS","Clientes":"S01-42363","Clientes_Descripcion":"CHUBB SEGUROS MEXICO","Folio":"RI0000122475","Fecha":"2026-06-25","Fecha_Venc":"2026-07-10","Condiciones_Pago":"NA","Rango_Vencido":"Por Vencer","Vencido_Por_Vencer":"Por Vencer","Area_de_Negocio":"Refacciones","Tipo_de_Movimiento":"Factura","Clasificacion_de_Cartera":"Aplicado","Cuenta_Contable_CXC":"CUENTAS POR COBRAR REFACCIONES","Fec_iniOP":"2026-07-01","Fec_finOP":"2026-07-02","Nombre_Mes":"07","Nombre_Mes_Descripcion":"Jul","Fecha_Recepcion_Servicio":"1900-01-01","Marcaje":"SIN FECHA","VIN":"NA","Tipo_de_Vehiculo":"NA","Ano_Modelo":"NA","Monto_Pagado":"SIN PAGOS","Dias_Vencido":-8,"Cargos_Creditos":0,"Saldo":568.4000244140625,"Saldo_Vencido":0,"Saldo_por_Vencer":568.4000244140625,"Monto_Original":568.4000244140625,"Dias_en_Taller":0,"Dias_Antiguedad":7},{"date_key":"2026-07-01","Compania":"Distribuidora Volkswagen Lomas","Sucursal":"VOLKSWAGEN Lomas","Company":"VW LOMAS","Clientes":"S01-42363","Clientes_Descripcion":"CHUBB SEGUROS MEXICO","Folio":"RI0000122470","Fecha":"2026-06-25","Fecha_Venc":"2026-07-10","Condiciones_Pago":"NA","Rango_Vencido":"Por Vencer","Vencido_Por_Vencer":"Por Vencer","Area_de_Negocio":"Refacciones","Tipo_de_Movimiento":"Factura","Clasificacion_de_Cartera":"Aplicado","Cuenta_Contable_CXC":"CUENTAS POR COBRAR REFACCIONES","Fec_iniOP":"2026-07-01","Fec_finOP":"2026-07-02","Nombre_Mes":"07","Nombre_Mes_Descripcion":"Jul","Fecha_Recepcion_Servicio":"1900-01-01","Marcaje":"SIN FECHA","VIN":"NA","Tipo_de_Vehiculo":"NA","Ano_Modelo":"NA","Monto_Pagado":"SIN PAGOS","Dias_Vencido":-8,"Cargos_Creditos":0,"Saldo":348,"Saldo_Vencido":0,"Saldo_por_Vencer":348,"Monto_Original":348,"Dias_en_Taller":0,"Dias_Antiguedad":7},{"date_key":"2026-07-01","Compania":"Distribuidora Volkswagen Lomas","Sucursal":"VOLKSWAGEN Lomas","Company":"VW LOMAS","Clientes":"S01-42363","Clientes_Descripcion":"CHUBB SEGUROS MEXICO","Folio":"RI0000122468","Fecha":"2026-06-25","Fecha_Venc":"2026-07-10","Condiciones_Pago":"NA","Rango_Vencido":"Por Vencer","Vencido_Por_Vencer":"Por Vencer","Area_de_Negocio":"Refacciones","Tipo_de_Movimiento":"Factura","Clasificacion_de_Cartera":"Aplicado","Cuenta_Contable_CXC":"CUENTAS POR COBRAR REFACCIONES","Fec_iniOP":"2026-07-01","Fec_finOP":"2026-07-02","Nombre_Mes":"07","Nombre_Mes_Descripcion":"Jul","Fecha_Recepcion_Servicio":"1900-01-01","Marcaje":"SIN FECHA","VIN":"NA","Tipo_de_Vehiculo":"NA","Ano_Modelo":"NA","Monto_Pagado":"SIN PAGOS","Dias_Vencido":-8,"Cargos_Creditos":0,"Saldo":245.9199981689453,"Saldo_Vencido":0,"Saldo_por_Vencer":245.9199981689453,"Monto_Original":245.9199981689453,"Dias_en_Taller":0,"Dias_Antiguedad":7},{"date_key":"2026-07-01","Compania":"Distribuidora Volkswagen Lomas","Sucursal":"VOLKSWAGEN Lomas","Company":"VW LOMAS","Clientes":"S01-42363","Clientes_Descripcion":"CHUBB SEGUROS MEXICO","Folio":"RI0000122466","Fecha":"2026-06-25","Fecha_Venc":"2026-07-10","Condiciones_Pago":"NA","Rango_Vencido":"Por Vencer","Vencido_Por_Vencer":"Por Vencer","Area_de_Negocio":"Refacciones","Tipo_de_Movimiento":"Factura","Clasificacion_de_Cartera":"Aplicado","Cuenta_Contable_CXC":"CUENTAS POR COBRAR REFACCIONES","Fec_iniOP":"2026-07-01","Fec_finOP":"2026-07-02","Nombre_Mes":"07","Nombre_Mes_Descripcion":"Jul","Fecha_Recepcion_Servicio":"1900-01-01","Marcaje":"SIN FECHA","VIN":"NA","Tipo_de_Vehiculo":"NA","Ano_Modelo":"NA","Monto_Pagado":"SIN PAGOS","Dias_Vencido":-8,"Cargos_Creditos":0,"Saldo":348,"Saldo_Vencido":0,"Saldo_por_Vencer":348,"Monto_Original":348,"Dias_en_Taller":0,"Dias_Antiguedad":7},{"date_key":"2026-07-01","Compania":"Distribuidora Volkswagen Lomas","Sucursal":"VOLKSWAGEN Lomas","Company":"VW LOMAS","Clientes":"S01-42363","Clientes_Descripcion":"CHUBB SEGUROS MEXICO","Folio":"RI0000122465","Fecha":"2026-06-25","Fecha_Venc":"2026-07-10","Condiciones_Pago":"NA","Rango_Vencido":"Por Vencer","Vencido_Por_Vencer":"Por Vencer","Area_de_Negocio":"Refacciones","Tipo_de_Movimiento":"Factura","Clasificacion_de_Cartera":"Aplicado","Cuenta_Contable_CXC":"CUENTAS POR COBRAR REFACCIONES","Fec_iniOP":"2026-07-01","Fec_finOP":"2026-07-02","Nombre_Mes":"07","Nombre_Mes_Descripcion":"Jul","Fecha_Recepcion_Servicio":"1900-01-01","Marcaje":"SIN FECHA","VIN":"NA","Tipo_de_Vehiculo":"NA","Ano_Modelo":"NA","Monto_Pagado":"SIN PAGOS","Dias_Vencido":-8,"Cargos_Creditos":0,"Saldo":1067.199951171875,"Saldo_Vencido":0,"Saldo_por_Vencer":1067.199951171875,"Monto_Original":1067.199951171875,"Dias_en_Taller":0,"Dias_Antiguedad":7},{"date_key":"2026-07-01","Compania":"Distribuidora Volkswagen Lomas","Sucursal":"VOLKSWAGEN Lomas","Company":"VW LOMAS","Clientes":"S01-42363","Clientes_Descripcion":"CHUBB SEGUROS MEXICO","Folio":"RI0000122462","Fecha":"2026-06-25","Fecha_Venc":"2026-07-10","Condiciones_Pago":"NA","Rango_Vencido":"Por Vencer","Vencido_Por_Vencer":"Por Vencer","Area_de_Negocio":"Refacciones","Tipo_de_Movimiento":"Factura","Clasificacion_de_Cartera":"Aplicado","Cuenta_Contable_CXC":"CUENTAS POR COBRAR REFACCIONES","Fec_iniOP":"2026-07-01","Fec_finOP":"2026-07-02","Nombre_Mes":"07","Nombre_Mes_Descripcion":"Jul","Fecha_Recepcion_Servicio":"1900-01-01","Marcaje":"SIN FECHA","VIN":"NA","Tipo_de_Vehiculo":"NA","Ano_Modelo":"NA","Monto_Pagado":"SIN PAGOS","Dias_Vencido":-8,"Cargos_Creditos":0,"Saldo":1020.7999877929688,"Saldo_Vencido":0,"Saldo_por_Vencer":1020.7999877929688,"Monto_Original":1020.7999877929688,"Dias_en_Taller":0,"Dias_Antiguedad":7},{"date_key":"2026-07-01","Compania":"Distribuidora Volkswagen Lomas","Sucursal":"VOLKSWAGEN Lomas","Company":"VW LOMAS","Clientes":"S01-42363","Clientes_Descripcion":"CHUBB SEGUROS MEXICO","Folio":"RI0000122459","Fecha":"2026-06-25","Fecha_Venc":"2026-07-10","Condiciones_Pago":"NA","Rango_Vencido":"Por Vencer","Vencido_Por_Vencer":"Por Vencer","Area_de_Negocio":"Refacciones","Tipo_de_Movimiento":"Factura","Clasificacion_de_Cartera":"Aplicado","Cuenta_Contable_CXC":"CUENTAS POR COBRAR REFACCIONES","Fec_iniOP":"2026-07-01","Fec_finOP":"2026-07-02","Nombre_Mes":"07","Nombre_Mes_Descripcion":"Jul","Fecha_Recepcion_Servicio":"1900-01-01","Marcaje":"SIN FECHA","VIN":"NA","Tipo_de_Vehiculo":"NA","Ano_Modelo":"NA","Monto_Pagado":"SIN PAGOS","Dias_Vencido":-8,"Cargos_Creditos":0,"Saldo":1136.800048828125,"Saldo_Vencido":0,"Saldo_por_Vencer":1136.800048828125,"Monto_Original":1136.800048828125,"Dias_en_Taller":0,"Dias_Antiguedad":7},{"date_key":"2026-07-01","Compania":"Distribuidora Volkswagen Lomas","Sucursal":"VOLKSWAGEN Lomas","Company":"VW LOMAS","Clientes":"S01-42363","Clientes_Descripcion":"CHUBB SEGUROS MEXICO","Folio":"RI0000122430","Fecha":"2026-06-24","Fecha_Venc":"2026-07-09","Condiciones_Pago":"NA","Rango_Vencido":"Por Vencer","Vencido_Por_Vencer":"Por Vencer","Area_de_Negocio":"Refacciones","Tipo_de_Movimiento":"Factura","Clasificacion_de_Cartera":"Aplicado","Cuenta_Contable_CXC":"CUENTAS POR COBRAR REFACCIONES","Fec_iniOP":"2026-07-01","Fec_finOP":"2026-07-02","Nombre_Mes":"07","Nombre_Mes_Descripcion":"Jul","Fecha_Recepcion_Servicio":"1900-01-01","Marcaje":"SIN FECHA","VIN":"NA","Tipo_de_Vehiculo":"NA","Ano_Modelo":"NA","Monto_Pagado":"SIN PAGOS","Dias_Vencido":-7,"Cargos_Creditos":0,"Saldo":754,"Saldo_Vencido":0,"Saldo_por_Vencer":754,"Monto_Original":754,"Dias_en_Taller":0,"Dias_Antiguedad":8},{"date_key":"2026-07-01","Compania":"Distribuidora Volkswagen Lomas","Sucursal":"VOLKSWAGEN Lomas","Company":"VW LOMAS","Clientes":"S01-42363","Clientes_Descripcion":"CHUBB SEGUROS MEXICO","Folio":"RI0000122429","Fecha":"2026-06-24","Fecha_Venc":"2026-07-09","Condiciones_Pago":"NA","Rango_Vencido":"Por Vencer","Vencido_Por_Vencer":"Por Vencer","Area_de_Negocio":"Refacciones","Tipo_de_Movimiento":"Factura","Clasificacion_de_Cartera":"Aplicado","Cuenta_Contable_CXC":"CUENTAS POR COBRAR REFACCIONES","Fec_iniOP":"2026-07-01","Fec_finOP":"2026-07-02","Nombre_Mes":"07","Nombre_Mes_Descripcion":"Jul","Fecha_Recepcion_Servicio":"1900-01-01","Marcaje":"SIN FECHA","VIN":"NA","Tipo_de_Vehiculo":"NA","Ano_Modelo":"NA","Monto_Pagado":"SIN PAGOS","Dias_Vencido":-7,"Cargos_Creditos":0,"Saldo":1890.800048828125,"Saldo_Vencido":0,"Saldo_por_Vencer":1890.800048828125,"Monto_Original":1890.800048828125,"Dias_en_Taller":0,"Dias_Antiguedad":8},{"date_key":"2026-07-01","Compania":"Distribuidora Volkswagen Lomas","Sucursal":"VOLKSWAGEN Lomas","Company":"VW LOMAS","Clientes":"S01-42363","Clientes_Descripcion":"CHUBB SEGUROS MEXICO","Folio":"RI0000122421","Fecha":"2026-06-24","Fecha_Venc":"2026-07-09","Condiciones_Pago":"NA","Rango_Vencido":"Por Vencer","Vencido_Por_Vencer":"Por Vencer","Area_de_Negocio":"Refacciones","Tipo_de_Movimiento":"Factura","Clasificacion_de_Cartera":"Aplicado","Cuenta_Contable_CXC":"CUENTAS POR COBRAR REFACCIONES","Fec_iniOP":"2026-07-01","Fec_finOP":"2026-07-02","Nombre_Mes":"07","Nombre_Mes_Descripcion":"Jul","Fecha_Recepcion_Servicio":"1900-01-01","Marcaje":"SIN FECHA","VIN":"NA","Tipo_de_Vehiculo":"NA","Ano_Modelo":"NA","Monto_Pagado":"SIN PAGOS","Dias_Vencido":-7,"Cargos_Creditos":0,"Saldo":1426.800048828125,"Saldo_Vencido":0,"Saldo_por_Vencer":1426.800048828125,"Monto_Original":1426.800048828125,"Dias_en_Taller":0,"Dias_Antiguedad":8},{"date_key":"2026-07-01","Compania":"Distribuidora Volkswagen Lomas","Sucursal":"VOLKSWAGEN Lomas","Company":"VW LOMAS","Clientes":"S01-42363","Clientes_Descripcion":"CHUBB SEGUROS MEXICO","Folio":"RI0000122401","Fecha":"2026-06-23","Fecha_Venc":"2026-07-08","Condiciones_Pago":"NA","Rango_Vencido":"Por Vencer","Vencido_Por_Vencer":"Por Vencer","Area_de_Negocio":"Refacciones","Tipo_de_Movimiento":"Factura","Clasificacion_de_Cartera":"Aplicado","Cuenta_Contable_CXC":"CUENTAS POR COBRAR REFACCIONES","Fec_iniOP":"2026-07-01","Fec_finOP":"2026-07-02","Nombre_Mes":"07","Nombre_Mes_Descripcion":"Jul","Fecha_Recepcion_Servicio":"1900-01-01","Marcaje":"SIN FECHA","VIN":"NA","Tipo_de_Vehiculo":"NA","Ano_Modelo":"NA","Monto_Pagado":"SIN PAGOS","Dias_Vencido":-6,"Cargos_Creditos":0,"Saldo":2030,"Saldo_Vencido":0,"Saldo_por_Vencer":2030,"Monto_Original":2030,"Dias_en_Taller":0,"Dias_Antiguedad":9}],"meta":{"total":null,"has_more":false,"next_offset":null}}